django_email/__init__.py
django_email/apps.py
django_email/djemail.py
django_email/exceptions.py
django_email/utils.py
django_email/templates/__init__.py
django_email/templates/email/__init__.py
django_email/templates/email/base.html
django_email/templates/email/base.txt
django_email-0.1.8.dist-info/DESCRIPTION.rst
django_email-0.1.8.dist-info/METADATA
django_email-0.1.8.dist-info/RECORD
django_email-0.1.8.dist-info/WHEEL
django_email-0.1.8.dist-info/metadata.json
django_email-0.1.8.dist-info/top_level.txt
